pyteaser.py
setup.py
goose/__init__.py
goose/article.py
goose/cleaners.py
goose/configuration.py
goose/crawler.py
goose/extractors.py
goose/network.py
goose/outputformatters.py
goose/parsers.py
goose/text.py
goose/version.py
goose/images/__init__.py
goose/images/extractors.py
goose/images/image.py
goose/images/utils.py
goose/resources/images/known-image-css.txt
goose/resources/text/stopwords-ar.txt
goose/resources/text/stopwords-de.txt
goose/resources/text/stopwords-en.txt
goose/resources/text/stopwords-es.txt
goose/resources/text/stopwords-fr.txt
goose/resources/text/stopwords-it.txt
goose/resources/text/stopwords-sv.txt
goose/resources/text/stopwords-zh.txt
goose/utils/__init__.py
goose/utils/encoding.py
goose/videos/__init__.py
goose/videos/extractors.py
goose/videos/videos.py
pyteaser.egg-info/PKG-INFO
pyteaser.egg-info/SOURCES.txt
pyteaser.egg-info/dependency_links.txt
pyteaser.egg-info/requires.txt
pyteaser.egg-info/top_level.txt