Metadata-Version: 1.0
Name: pyteaser
Version: 1.0
Summary: PyTeaser is based on the original TextTeaser project written in Scala by Mojojolo. It's completely re-written in Python.
Home-page: https://github.com/xiaoxu193/PyTeaser
Author: Xiao Xu
Author-email: xx56@cornell.edu
License: MIT
Platform: UNKNOWN
